molfidget/__init__.py
molfidget/atom.py
molfidget/bond.py
molfidget/config.py
molfidget/constants.py
molfidget/labeled_scene_viewer.py
molfidget/molecule.py
molfidget/molfidget.py
molfidget/shape.py
molfidget-1.0.0.dist-info/METADATA
molfidget-1.0.0.dist-info/WHEEL
molfidget-1.0.0.dist-info/entry_points.txt
molfidget-1.0.0.dist-info/licenses/LICENSE
molfidget-1.0.0.dist-info/RECORD
