Metadata-Version: 2.4
Name: molfidget
Version: 1.0.0
Summary: A molecular modeler of 3D printable models from the MOL/PDB format.
License-File: LICENSE
Author: Ryosuke Tajima
Author-email: tajima.ryosuke@techmagic.co.jp
Requires-Python: >=3.12,<4.0
Classifier: Programming Language :: Python :: 3
Classifier: Programming Language :: Python :: 3.12
Classifier: Programming Language :: Python :: 3.13
Classifier: Programming Language :: Python :: 3.14
Requires-Dist: argcomplete (>=3.1.0,<4.0.0)
Requires-Dist: dacite (>=1.9.2,<2.0.0)
Requires-Dist: from-dict (>=0.5.0,<0.6.0)
Requires-Dist: manifold3d (>=3.1.0,<4.0.0)
Requires-Dist: pyglet (<2)
Requires-Dist: pyyaml (>=6.0.1,<7.0.0)
Requires-Dist: ruamel-yaml (>=0.18.16,<0.19.0)
Requires-Dist: scipy (>=1.15.3,<2.0.0)
Requires-Dist: trimesh (>=4.6.9,<5.0.0)
